{"cameraMode":{"drawMode":0,"name":"Shaded","section":"Shading Mode"},"sceneLighting":true,"audioPlay":false,"sceneViewState":{"m_AlwaysRefresh":false,"showFog":true,"showSkybox":true,"showFlares":true,"showImageEffects":true,"showParticleSystems":true,"showVisualEffectGraphs":true,"m_FxEnabled":true},"in2DMode":false,"pivot":{"x":21.977807998657228,"y":-1.3278623819351197,"z":-6.163041591644287},"rotation":{"x":-0.170134037733078,"y":-0.6083396077156067,"z":0.13559715449810029,"w":-0.7632980346679688},"size":9.998250961303711,"orthographic":false}